tests/__init__.py
uniqcharstest11-1.0.dist-info/LICENSE
uniqcharstest11-1.0.dist-info/METADATA
uniqcharstest11-1.0.dist-info/WHEEL
uniqcharstest11-1.0.dist-info/entry_points.txt
uniqcharstest11-1.0.dist-info/top_level.txt
uniqcharstest11-1.0.dist-info/RECORD
